guardog/__init__.py
guardog/guardog.py
guardog/settings.py
guardog/warnings.py
guardog-1.3.0.dist-info/WHEEL
guardog-1.3.0.dist-info/METADATA
guardog-1.3.0.dist-info/RECORD
